{
    "last_update": "2024-06-08 17:38:50",
    "ac_power": 1052.44,
    "month_name": "JUNE",
    "current_year": 2024,
    "carbon": 3980,
    "alberi": 5443,
    "t_evita": 3353,
    "total_dayenergy": [
        "9953.900000000038"
    ],
    "life_energy": 8382325,
    "acEnergy_hour_day": [
        "6",
        "7",
        "8",
        "9",
        "10",
        "11",
        "12",
        "13",
        "14",
        "15"
    ],
    "acEnergy_hour": [
        "8.59999999991851",
        "153.800000000032",
        "423.6000000000349",
        "971.2999999999593",
        "1298.500000000102",
        "1641.0999999999622",
        "1465.9999999999418",
        "1457.4000000000087",
        "675.0000000000291",
        "812.8999999999942"
    ],
    "all_years_list": [
        "2023",
        "2024"
    ],
    "all_years_data": [
        "3449970.699999999",
        "4932354.299999998"
    ],
    "all_daymonth_list": [
        "01",
        "02",
        "03",
        "04",
        "05",
        "06",
        "07",
        "08"
    ],
    "all_daymonth_data": [
        "12860.300000000016",
        "117408.7",
        "109917",
        "15751.999999999984",
        "19736.90000000001",
        "98864.30000000002",
        "16896.699999999983",
        "9953.900000000038"
    ],
    "all_monthyear_list": [
        "September",
        "October",
        "November",
        "December",
        "January",
        "February",
        "March",
        "April",
        "May",
        "June"
    ],
    "all_monthyear_data": [
        "5535.099999999991",
        "174602.99999999994",
        "176055.80000000005",
        "3093776.799999999",
        "251258.60000000003",
        "256034.9",
        "363571.4",
        "2110736.9",
        "1558868.6999999983",
        "391883.8000000001"
    ],
    "temperature_2m": "26.5 \u00b0C",
    "relative_humidity_2m": "69 %",
    "apparent_temperature": "30.1 \u00b0C",
    "is_day": 1,
    "weather_exp": "Cloudy",
    "precipitation": "0.0 mm",
    "rain": "0.0 mm",
    "showers": "0.0 mm",
    "snowfall": "0.0 cm",
    "weather_code": "http://openweathermap.org/img/wn/03d@2x.png",
    "cloud_cover": "100 %",
    "pressure_msl": "1011.0 hPa",
    "surface_pressure": "994.8 hPa",
    "wind_speed_10m": "3.8 km/h",
    "wind_direction_10m": "253 \u00b0"
}