{
    "last_update": "2025-02-18 20:48:51",
    "ac_power": 0.0,
    "month_name": "FEBRUARY",
    "current_year": 2025,
    "carbon": 6361,
    "alberi": 8699,
    "t_evita": 5358,
    "total_dayenergy": 3751.100000000035,
    "life_energy": 13395875,
    "acEnergy_hour_day": [
        "7",
        "8",
        "9",
        "10",
        "11",
        "12",
        "13",
        "14",
        "15",
        "16",
        "17"
    ],
    "acEnergy_hour": [
        "26.800000000090225",
        "194.89999999995047",
        "455.8000000000902",
        "688.5999999998749",
        "645.3999999999651",
        "524.5000000000582",
        "479.29999999993015",
        "420.1000000000786",
        "241.4999999999418",
        "73.10000000004948",
        "1.1000000000058208"
    ],
    "all_years_list": [
        "2023",
        "2024",
        "2025"
    ],
    "all_years_data": [
        "3449970.699999999",
        "9652591.999999998",
        "293312.3"
    ],
    "all_daymonth_list": [
        "01",
        "02",
        "03",
        "04",
        "05",
        "06",
        "07",
        "08",
        "09",
        "10",
        "11",
        "12",
        "13",
        "14",
        "15",
        "16",
        "17",
        "18"
    ],
    "all_daymonth_data": [
        "1018.1000000000496",
        "13705.799999999886",
        "14031.30000000022",
        "13575.799999999872",
        "14438.00000000003",
        "14587.400000000009",
        "5844.299999999916",
        "2623.400000000067",
        "1273.1000000000058",
        "2977.0999999999185",
        "1431.100000000035",
        "2652.5",
        "3760.400000000169",
        "2954.299999999872",
        "14116.69999999994",
        "5130.499999999985",
        "3817.100000000064",
        "3751.100000000035"
    ],
    "all_monthyear_list": [
        "September",
        "October",
        "November",
        "December",
        "January",
        "February",
        "March",
        "April",
        "May",
        "June",
        "July",
        "August",
        "September",
        "October",
        "November",
        "December",
        "January",
        "February"
    ],
    "all_monthyear_data": [
        "5535.099999999991",
        "174602.99999999994",
        "176055.80000000005",
        "3093776.799999999",
        "251258.60000000003",
        "256034.9",
        "363571.4",
        "2110736.9",
        "1558868.6999999983",
        "2143373.299999999",
        "1008722.1",
        "743196.2999999998",
        "454279.3999999999",
        "247731.80000000005",
        "296587.80000000016",
        "218230.7999999999",
        "172600.99999999994",
        "120711.30000000006"
    ],
    "temperature_2m": "4.2 \u00b0C",
    "relative_humidity_2m": "61 %",
    "apparent_temperature": "0.7 \u00b0C",
    "is_day": 0,
    "weather_exp": "Cloudy",
    "precipitation": "0.0 mm",
    "rain": "0.0 mm",
    "showers": "0.0 mm",
    "snowfall": "0.0 cm",
    "weather_code": "http://openweathermap.org/img/wn/03n@2x.png",
    "cloud_cover": "100 %",
    "pressure_msl": "1025.9 hPa",
    "surface_pressure": "1008.1 hPa",
    "wind_speed_10m": "6.8 km/h",
    "wind_direction_10m": "122 \u00b0"
}