[
  {
    "CTR + Percorso cartella": "IND10_029 (T:\\CLIENTI\\CANTIERI CHIUSI\\09 - GRANDI IMPIANTI\\2010)",
    "Nominativo": "Soc. Agr. Santamaria",
    "Coordinate X": "41.045676",
    "Coordinate Y": "17.017383",
    "Tipologia": "Noicattaro, Bari",
    "Tipologia Description": "Impianto fotovoltaico in campo agricolo: sostenibilit? senza rinunciare alle colture.",
    "Categoria": "Agrivoltaico",
    "Potenza": "996,15 kWp",
    "Power": 996.15,
    "Producibilit?": 1350,
    "Energia Prodotta": "1.345 MWh/anno",
    "Energia Prodotta 25": "33.620 MWh",
    "Alberi": "51.340 alberi",
    "CO2  risparmiato": "8.573 ton.",
    "Risparmio": "? 6.724.013",
    "TEP": "2.891 TEP",
    "Link a pagina del Progetto": "x",
    "Foto1": "https://www.myenergy.it/wp-content/uploads/2025/04/impianto-agrivoltaico-scaled.jpg",
    "Foto2": "https://www.myenergy.it/wp-content/uploads/2025/04/agrivoltaico-e-colture-sostenibili-scaled.jpg",
    "Foto3": "https://www.myenergy.it/wp-content/uploads/2025/04/fotovoltaico-terreno-agricolo-scaled.jpg",
    "Gallery": "https://www.myenergy.it/wp-content/uploads/2025/04/colture-e-fotovoltaico-scaled.jpg,https://www.myenergy.it/wp-content/uploads/2025/04/fotovoltaico-agricolo-a-terra-scaled.jpg",
    "": " ",
    "latitude": "41.045676",
    "longitude": "17.017383"
  },
  {
    "CTR + Percorso cartella": "EST19_003",
    "Nominativo": "MEL",
    "Coordinate X": "35.807933",
    "Coordinate Y": "14.527015",
    "Tipologia": "Birzebbugia, Malta",
    "Tipologia Description": "Malta spinge verso la sostenibilit? con un impianto di 7.260 moduli fotovoltaici.",
    "Categoria": "Fotovoltaico Estero",
    "Potenza": "2,4 MWp",
    "Power": 2400,
    "Producibilit?": 1604,
    "Energia Prodotta": "3.850 MWh/anno",
    "Energia Prodotta 25": "96.240 MWh",
    "Alberi": "146.960 alberi",
    "CO2  risparmiato": "36.575 ton.",
    "Risparmio": "? 9.624.000",
    "TEP": "8.275 TEP",
    "Link a pagina del Progetto": "x",
    "Foto1": "https://www.myenergy.it/wp-content/uploads/2025/04/impianto-fotovoltaico-malta-scaled.jpg",
    "Foto2": "https://www.myenergy.it/wp-content/uploads/2025/04/installazione-impianto-fotovoltaico-a-malta-scaled.jpg",
    "Foto3": "https://www.myenergy.it/wp-content/uploads/2025/04/installazione-cabina-fotovoltaico-scaled.jpg",
    "Gallery": "https://www.myenergy.it/wp-content/uploads/2025/04/installazione-fotovoltaico-a-malta-scaled.jpg,https://www.myenergy.it/wp-content/uploads/2025/04/moduli-fotovoltaici-canadian-solar-scaled.jpg,https://www.myenergy.it/wp-content/uploads/2025/04/installazione-cavi-in-cabina-fotovoltaica-scaled.jpg",
    "": " ",
    "latitude": "35.807933",
    "longitude": "14.527015"
  },
  {
    "CTR + Percorso cartella": "IMP22_203",
    "Nominativo": "Merbag S.p.A. - Mercedes",
    "Coordinate X": "45.507452507564366",
    "Coordinate Y": "9.099550272971014",
    "Tipologia": "Milano",
    "Tipologia Description": "x",
    "Categoria": "Fotovoltaico Industriale",
    "Potenza": "626,48 kWp",
    "Power": 626.48,
    "Producibilit?": 1135,
    "Energia Prodotta": "711 MWh/anno",
    "Energia Prodotta 25": "17.776 MWh",
    "Alberi": "27.150 alberi",
    "CO2  risparmiato": "4.533 ton.",
    "Risparmio": "? 3.555.274",
    "TEP": "1.528 TEP",
    "Link a pagina del Progetto": "x",
    "Foto1": "https://www.myenergy.it/wp-content/uploads/2025/04/COVER-scaled.jpg",
    "": " ",
    "latitude": "45.507452507564366",
    "longitude": "9.099550272971014"
  },
  {
    "CTR + Percorso cartella": "IMP23_020 - VALISI ANGELO",
    "Nominativo": "Impianto Residenziale",
    "Coordinate X": "45.458184257269565",
    "Coordinate Y": "8.887085996359733",
    "Tipologia": "Magenta, Milano",
    "Tipologia Description": "x",
    "Categoria": "Fotovoltaico Residenziale",
    "Power": "4,5",
    "Producibilit?": 1070,
    "Energia Prodotta": "5 MWh/anno",
    "Energia Prodotta 25": "120 MWh",
    "Alberi": "190 alberi",
    "CO2  risparmiato": "30.696 kg",
    "Risparmio": "? 24.075",
    "TEP": "10 TEP",
    "Link a pagina del Progetto": "x",
    "latitude": "45.458184257269565",
    "longitude": "8.887085996359733"
  },
  {
    "CTR + Percorso cartella": "SRES24_029 - PLESTRA FRANCESCO (Plestra) (tecnico solutions:\\CLIENTI\\7 - RESIDENZIALI",
    "Nominativo": "Efficientamento Residenziale",
    "Coordinate X": "45.324317316181876",
    "Coordinate Y": "9.01438050653722",
    "Tipologia": "Bubbiano, Milano",
    "Tipologia Description": "Myenergy ha trasformato questa casa indipendente con un intervento energetico completo.",
    "Categoria": "Efficientamento Energetico",
    "Power": 8.8,
    "Producibilit?": 1093,
    "Energia Prodotta": "9.618 kWh/anno",
    "Energia Prodotta 25": "240.460 kWh",
    "Alberi": "367 alberi",
    "CO2  risparmiato": "61.310 kg",
    "Risparmio": "? 48.090",
    "TEP": "21 TEP",
    "Link a pagina del Progetto": "x",
    "": " ",
    "latitude": "45.324317316181876",
    "longitude": "9.01438050653722"
  },
  {
    "CTR + Percorso cartella": "BAN24_001",
    "Nominativo": "Grandi Stazioni Rail",
    "Coordinate X": "41.9075",
    "Coordinate Y": "12.4900",
    "Tipologia": "Roma",
    "Tipologia Description": "x",
    "Categoria": "Pubblica Amministrazione",
    "Power": 488.52,
    "Producibilit?": 1433,
    "Energia Prodotta": "700 MWh/anno",
    "Energia Prodotta 25": "17.501 MWh",
    "Alberi": "26.730 alberi",
    "CO2  risparmiato": "4.463 ton.",
    "Risparmio": "? 3.500.246",
    "TEP": "1.505 TEP",
    "Link a pagina del Progetto": "x",
    "Foto1": "https://www.myenergy.it/wp-content/uploads/2025/04/68.-14-mag-24.jpg",
    "Foto2": "https://www.myenergy.it/wp-content/uploads/2025/04/81.-22-mag-24.jpg",
    "Foto3": "https://www.myenergy.it/wp-content/uploads/2025/04/80.-22-mag-24.jpg",
    "Gallery": "https://www.myenergy.it/wp-content/uploads/2025/04/89.-24-mag-24.jpg,https://www.myenergy.it/wp-content/uploads/2025/04/82.-22-mag-24.jpg",
    "": " ",
    "latitude": "41.9075",
    "longitude": "12.4900"
  },
  {
    "CTR + Percorso cartella": "Z:\\CLIENTI\\13 - ECOBONUS\\2023\\ECO23_001 - Condominio VIA TRIESTE\\Documentazione completa",
    "Nominativo": "Condominio Superbonus",
    "Coordinate X": "45.41307",
    "Coordinate Y": "9.26737",
    "Tipologia": "San Giuliano Milanese",
    "Tipologia Description": "x",
    "Categoria": "Superbonus",
    "Power": 70.52,
    "Producibilit?": 1076,
    "Energia Prodotta": "75.880 kWh/anno",
    "Energia Prodotta 25": "1.896.988 kWh",
    "Alberi": "2.900 alberi",
    "CO2  risparmiato": "484 ton.",
    "Risparmio": "? 379.398",
    "TEP": "163 TEP",
    "Link a pagina del Progetto": "v",
    "Foto1": "https://www.myenergy.it/wp-content/uploads/2025/04/Moduli-1-scaled.jpg",
    "Foto2": "https://www.myenergy.it/wp-content/uploads/2025/04/Moduli-2-scaled.jpg",
    "": " ",
    "latitude": "45.41307",
    "longitude": "9.26737"
  },
  {
    "CTR + Percorso cartella": "Z:\\CLIENTI\\13 - ECOBONUS\\2023\\ECO23_002 - Condominio DI GIOIA\\Documentazione completa",
    "Nominativo": "Condominio Superbonus",
    "Coordinate X": "41.09481",
    "Coordinate Y": "16.96656",
    "Tipologia": "Bari",
    "Tipologia Description": "x",
    "Categoria": "Superbonus",
    "Power": 21.6,
    "Producibilit?": 1148,
    "Energia Prodotta": "24.797 kWh/anno",
    "Energia Prodotta 25": "619.920 kWh",
    "Alberi": "950 alberi",
    "CO2  risparmiato": "158 ton.",
    "Risparmio": "? 123.984",
    "TEP": "53 TEP",
    "Link a pagina del Progetto": "v",
    "Foto1": "https://www.myenergy.it/wp-content/uploads/2025/04/IMG-20230512-WA0040.jpg",
    "Foto2": "https://www.myenergy.it/wp-content/uploads/2025/04/IMG-20230512-WA0039.jpg",
    "Foto3": "https://www.myenergy.it/wp-content/uploads/2025/04/IMG-20230512-WA0044.jpg",
    "": "ATTENZIONE:",
    "latitude": "41.09481",
    "longitude": "16.96656"
  },
  {
    "CTR + Percorso cartella": "Z:\\CLIENTI\\13 - ECOBONUS\\2022\\ECO22_013 - DAMIANO GIUSEPPE ANDREA\\Documentazione completa",
    "Nominativo": "Progetto Superbonus",
    "Coordinate X": "45.52522",
    "Coordinate Y": "9.38394",
    "Tipologia": "Gorgonzola, Milano",
    "Tipologia Description": "x",
    "Categoria": "Superbonus",
    "Power": 7.79,
    "Producibilit?": 1082,
    "Energia Prodotta": "8.429 kWh/anno",
    "Energia Prodotta 25": "210.720 kWh",
    "Alberi": "330 alberi",
    "CO2  risparmiato": "53.733 kg",
    "Risparmio": "? 42.144",
    "TEP": "18 TEP",
    "Link a pagina del Progetto": "v",
    "Foto1": "https://www.myenergy.it/wp-content/uploads/2025/04/WhatsApp-Image-2022-06-13-at-19.54.51-4.jpeg",
    "Foto2": "https://www.myenergy.it/wp-content/uploads/2025/04/WhatsApp-Image-2022-06-13-at-19.54.51-5.jpeg",
    "Foto3": "https://www.myenergy.it/wp-content/uploads/2025/04/WhatsApp-Image-2022-06-13-at-19.54.50-4.jpeg",
    "": "Tipologia invece ? Provincia",
    "latitude": "45.52522",
    "longitude": "9.38394"
  },
  {
    "CTR + Percorso cartella": "Z:\\CLIENTI\\13 - ECOBONUS\\2021\\ECO21_065 - DI FAZIO FRANCO\\Documentazione completa",
    "Nominativo": "Progetto Superbonus",
    "Coordinate X": "41.49175",
    "Coordinate Y": "13.78274",
    "Tipologia": "Villa Santa Lucia, Frosinone",
    "Tipologia Description": "x",
    "Categoria": "Superbonus",
    "Power": 8.3,
    "Producibilit?": 1184,
    "Energia Prodotta": "9.827 kWh/anno",
    "Energia Prodotta 25": "245.680 kWh",
    "Alberi": "380 alberi",
    "CO2  risparmiato": "62.648 kg",
    "Risparmio": "? 49.136",
    "TEP": "21 TEP",
    "Foto1": "https://www.myenergy.it/wp-content/uploads/2025/04/DJI_0468-scaled.jpg",
    "Foto2": "https://www.myenergy.it/wp-content/uploads/2025/04/DJI_0470-scaled.jpg",
    "Foto3": "https://www.myenergy.it/wp-content/uploads/2025/04/DJI_0473-scaled.jpg",
    "": "Attenzione alle categorie, devono essere uniche",
    "latitude": "41.49175",
    "longitude": "13.78274"
  },
  {
    "CTR + Percorso cartella": "Y:\\CLIENTI\\6 - ECOBONUS  SOLUTIONS\\2021\\SECO21_001 - PICCIONE MARIA PINA\\Documentazione completa",
    "Nominativo": "Piccione Maria Pina",
    "Coordinate X": "36.89838",
    "Coordinate Y": "14.43082",
    "Tipologia": "Vittoria, Ragusa",
    "Tipologia Description": "x",
    "Categoria": "Superbonus",
    "Power": 3.25,
    "Producibilit?": 1275,
    "Energia Prodotta": "4.144 kWh/anno",
    "Energia Prodotta 25": "103.594 kWh",
    "Alberi": "160 alberi",
    "CO2  risparmiato": "26.416 kg",
    "Risparmio": "? 20.719",
    "TEP": "9 TEP",
    "Foto1": "https://www.myenergy.it/wp-content/uploads/2025/04/f45eabba-155f-43d2-ac73-48ee81f8e570-1.jpg",
    "Foto2": "https://www.myenergy.it/wp-content/uploads/2025/04/PHOTO-2022-06-01-13-22-55-2.jpg",
    "Foto3": "https://www.myenergy.it/wp-content/uploads/2025/04/PHOTO-2022-06-01-13-22-55.jpg",
    "latitude": "36.89838",
    "longitude": "14.43082"
  },
  {
    "CTR + Percorso cartella": "Z:\\CLIENTI\\13 - ECOBONUS\\2021\\ECO21_068 - CONVERSANO FORTUNATO\\Documentazione completa",
    "Nominativo": "Conversano Fortunato",
    "Coordinate X": "41.00779",
    "Coordinate Y": "16.86656",
    "Tipologia": "Adelfia, Bari",
    "Tipologia Description": "x",
    "Categoria": "Superbonus",
    "Power": 8.2,
    "Producibilit?": 1224,
    "Energia Prodotta": "10.037 kWh/anno",
    "Energia Prodotta 25": "250.920 kWh",
    "Alberi": "390 alberi",
    "CO2  risparmiato": "63.985 kg",
    "Risparmio": "? 50.184",
    "TEP": "22 TEP",
    "Foto1": "https://www.myenergy.it/wp-content/uploads/2025/04/IMG-20220520-WA0003.jpg",
    "Foto2": "https://www.myenergy.it/wp-content/uploads/2025/04/IMG-20220520-WA0005.jpg",
    "Foto3": "https://www.myenergy.it/wp-content/uploads/2025/04/IMG-20220520-WA0007.jpg",
    "latitude": "41.00779",
    "longitude": "16.86656"
  },
  {
    "CTR + Percorso cartella": "IMP22_192 - DE MARCO CINOTTI",
    "Nominativo": "Impianto Residenziale",
    "Coordinate X": "41.87298",
    "Coordinate Y": "12.46872",
    "Tipologia": "Roma",
    "Tipologia Description": "x",
    "Categoria": "Fotovoltaico Residenziale",
    "Power": "6",
    "Producibilit?": 1066.6666666666667,
    "Energia Prodotta": "6 MWh/anno",
    "Energia Prodotta 25": "160 MWh",
    "Alberi": "250 alberi",
    "CO2  risparmiato": "40.800 kg",
    "Risparmio": "? 32.000",
    "TEP": "14 TEP",
    "Foto1": "https://www.myenergy.it/wp-content/uploads/2025/04/Qpahlb3Nxd8tpk2NflQId-scaled.jpg",
    "latitude": "41.87298",
    "longitude": "12.46872"
  },
  {
    "CTR + Percorso cartella": "IMP22_194 - GIULIONI LORIS (Stucchi-Giuliano)",
    "Nominativo": "Impianto Residenziale",
    "Coordinate X": "45.19811",
    "Coordinate Y": "11.29592",
    "Tipologia": "Angiari, Verona",
    "Tipologia Description": "x",
    "Categoria": "Fotovoltaico Residenziale",
    "Power": "7,2",
    "Producibilit?": 1000,
    "Energia Prodotta": "7 MWh/anno",
    "Energia Prodotta 25": "180 MWh",
    "Alberi": "280 alberi",
    "CO2  risparmiato": "45.900 kg",
    "Risparmio": "? 36.000",
    "TEP": "15 TEP",
    "Foto1": "https://www.myenergy.it/wp-content/uploads/2025/04/75eb880d-751c-46bb-b726-b2c6833da387.jpg",
    "Foto2": "https://www.myenergy.it/wp-content/uploads/2025/04/7da0dcb1-0395-42e9-93ab-28dbacbe9ef9.jpg",
    "latitude": "45.19811",
    "longitude": "11.29592"
  },
  {
    "CTR + Percorso cartella": "IMP22_195 - MONTELEONE MARIO",
    "Nominativo": "Impianto Residenziale",
    "Coordinate X": "41.975796231039276",
    "Coordinate Y": "12.629735384673197",
    "Tipologia": "Guidonia Montecelio, Roma",
    "Tipologia Description": "x",
    "Categoria": "Fotovoltaico Residenziale",
    "Power": "6",
    "Producibilit?": 1066.6666666666667,
    "Energia Prodotta": "6 MWh/anno",
    "Energia Prodotta 25": "160 MWh",
    "Alberi": "250 alberi",
    "CO2  risparmiato": "40.800 kg",
    "Risparmio": "? 32.000",
    "TEP": "14 TEP",
    "latitude": "41.975796231039276",
    "longitude": "12.629735384673197"
  },
  {
    "CTR + Percorso cartella": "IMP22_196 - GANDOLA STEFANIA (Stucchi-Giuliano)",
    "Nominativo": "Impianto Residenziale",
    "Coordinate X": "45.3544395191661",
    "Coordinate Y": "9.342376286457506",
    "Tipologia": "Vizzolo Predabissi, Milano",
    "Tipologia Description": "x",
    "Categoria": "Fotovoltaico Residenziale",
    "Power": "6,2",
    "Producibilit?": 1100,
    "Energia Prodotta": "7 MWh/anno",
    "Energia Prodotta 25": "171 MWh",
    "Alberi": "270 alberi",
    "CO2  risparmiato": "43.478 kg",
    "Risparmio": "? 34.100",
    "TEP": "15 TEP",
    "latitude": "45.3544395191661",
    "longitude": "9.342376286457506"
  },
  {
    "CTR + Percorso cartella": "IMP22_205 - MESCALCHIN VALTER",
    "Nominativo": "Impianto Residenziale",
    "Coordinate X": "45.373904023306764",
    "Coordinate Y": "12.094427094044178",
    "Tipologia": "Camponogara, Venezia",
    "Tipologia Description": "x",
    "Categoria": "Fotovoltaico Residenziale",
    "Power": "6",
    "Producibilit?": 1066.6666666666667,
    "Energia Prodotta": "6 MWh/anno",
    "Energia Prodotta 25": "160 MWh",
    "Alberi": "250 alberi",
    "CO2  risparmiato": "40.800 kg",
    "Risparmio": "? 32.000",
    "TEP": "14 TEP",
    "latitude": "45.373904023306764",
    "longitude": "12.094427094044178"
  },
  {
    "CTR + Percorso cartella": "IMP22_206 - EDILVENTANA S.U.R.L.S. - STRADIOTTI ITALO ALBERTO (Stucchi)",
    "Nominativo": "Impianto Residenziale",
    "Coordinate X": "40.894241227649026",
    "Coordinate Y": "16.71282069968882",
    "Tipologia": "Lagogemolo, Bari",
    "Tipologia Description": "x",
    "Categoria": "Fotovoltaico Residenziale",
    "Power": "5,74",
    "Producibilit?": 1193.3797909407665,
    "Energia Prodotta": "7 MWh/anno",
    "Energia Prodotta 25": "171 MWh",
    "Alberi": "270 alberi",
    "CO2  risparmiato": "43.669 kg",
    "Risparmio": "? 34.250",
    "TEP": "15 TEP",
    "latitude": "40.894241227649026",
    "longitude": "16.71282069968882"
  },
  {
    "CTR + Percorso cartella": "IMP22_208 - BROCCHI MAURIZIO (Stucchi-Giuliano)",
    "Nominativo": "Impianto Residenziale",
    "Coordinate X": "45.40138681024923",
    "Coordinate Y": "9.03554295290563",
    "Tipologia": "Gaggiano, Milano",
    "Tipologia Description": "x",
    "Categoria": "Fotovoltaico Residenziale",
    "Power": "6,56",
    "Producibilit?": 1062.5,
    "Energia Prodotta": "7 MWh/anno",
    "Energia Prodotta 25": "174 MWh",
    "Alberi": "270 alberi",
    "CO2  risparmiato": "44.434 kg",
    "Risparmio": "? 34.850",
    "TEP": "15 TEP",
    "latitude": "45.40138681024923",
    "longitude": "9.03554295290563"
  },
  {
    "CTR + Percorso cartella": "IMP23_002 - ROSCIANO MARIO (Stucchi-Giuliano)",
    "Nominativo": "Impianto Residenziale",
    "Coordinate X": "45.56544509951229",
    "Coordinate Y": "9.21893733673326",
    "Tipologia": "Cinisello Balsamo, Milano",
    "Tipologia Description": "x",
    "Categoria": "Fotovoltaico Residenziale",
    "Power": "6",
    "Producibilit?": 1066.6666666666667,
    "Energia Prodotta": "6 MWh/anno",
    "Energia Prodotta 25": "160 MWh",
    "Alberi": "250 alberi",
    "CO2  risparmiato": "40.800 kg",
    "Risparmio": "? 32.000",
    "TEP": "14 TEP",
    "latitude": "45.56544509951229",
    "longitude": "9.21893733673326"
  },
  {
    "CTR + Percorso cartella": "IMP23_010 - AGOSTINI MARIA ANTONIETTA",
    "Nominativo": "Impianto Residenziale",
    "Coordinate X": "41.75965825377753",
    "Coordinate Y": "12.6053948966236",
    "Tipologia": "Marino, Roma",
    "Tipologia Description": "x",
    "Categoria": "Fotovoltaico Residenziale",
    "Power": "8,2",
    "Producibilit?": 903.1707317073171,
    "Energia Prodotta": "7 MWh/anno",
    "Energia Prodotta 25": "185 MWh",
    "Alberi": "290 alberi",
    "CO2  risparmiato": "47.213 kg",
    "Risparmio": "? 37.030",
    "TEP": "16 TEP",
    "latitude": "41.75965825377753",
    "longitude": "12.6053948966236"
  },
  {
    "CTR + Percorso cartella": "IMP23_034 - ISICO SRL",
    "Nominativo": "Isico SRL",
    "Coordinate X": "45.4658",
    "Coordinate Y": "9.1900",
    "Tipologia": "Milano",
    "Tipologia Description": "x",
    "Categoria": "Fotovoltaico Industriale",
    "Power": "11,07",
    "Producibilit?": 981.2105,
    "Energia Prodotta": "11 MWh/anno",
    "Energia Prodotta 25": "272 MWh",
    "Alberi": "420 alberi",
    "CO2  risparmiato": "69.245 kg",
    "Risparmio": "? 54.310",
    "TEP": "23 TEP",
    "latitude": "45.4658",
    "longitude": "9.1900"
  },
  {
    "CTR + Percorso cartella": "IMP23_040 - IMMOUNO SRL",
    "Nominativo": "Immouno SRL",
    "Coordinate X": "45.1383",
    "Coordinate Y": "7.7725",
    "Tipologia": "Settimo Torinese, Torino",
    "Tipologia Description": "x",
    "Categoria": "Fotovoltaico Industriale",
    "Power": 63.232,
    "Producibilit?": 1076.0148,
    "Energia Prodotta": "68.039 kWh/anno",
    "Energia Prodotta 25": "1.700.964 kWh",
    "Alberi": "2.600 alberi",
    "CO2  risparmiato": "434 ton.",
    "Risparmio": "? 340.193",
    "TEP": "146 TEP",
    "latitude": "45.1383",
    "longitude": "7.7725"
  },
  {
    "CTR + Percorso cartella": "IMP24_001 - BENNET SPA Anzano del Parco",
    "Nominativo": "Bennet SPA",
    "Coordinate X": "45.7703",
    "Coordinate Y": "9.1994",
    "Tipologia": "Anzano del Parco, Como",
    "Tipologia Description": "x",
    "Categoria": "Fotovoltaico Industriale",
    "Power": 716.32,
    "Producibilit?": 963.1535,
    "Energia Prodotta": "690 MWh/anno",
    "Energia Prodotta 25": "17.248 MWh",
    "Alberi": "26.340 alberi",
    "CO2  risparmiato": "4.398 ton.",
    "Risparmio": "? 3.449.631",
    "TEP": "1.483 TEP",
    "latitude": "45.7703",
    "longitude": "9.1994"
  },
  {
    "CTR + Percorso cartella": "IMP24_002 - BENNET SPA San Martino Siccomario",
    "Nominativo": "Bennet SPA",
    "Coordinate X": "45.1603",
    "Coordinate Y": "9.1375",
    "Tipologia": "San Martino Siccomario, Pavia",
    "Tipologia Description": "x",
    "Categoria": "Fotovoltaico Industriale",
    "Power": 644.16,
    "Producibilit?": 1243.8333,
    "Energia Prodotta": "801 MWh/anno",
    "Energia Prodotta 25": "20.031 MWh",
    "Alberi": "30.590 alberi",
    "CO2  risparmiato": "5.108 ton.",
    "Risparmio": "? 4.006.138",
    "TEP": "1.722 TEP",
    "latitude": "45.1603",
    "longitude": "9.1375"
  },
  {
    "CTR + Percorso cartella": "IMP24_003 - BENNET SPA Cornaredo",
    "Nominativo": "Bennet SPA",
    "Coordinate X": "45.5039",
    "Coordinate Y": "9.0256",
    "Tipologia": "Cornaredo, Milano",
    "Tipologia Description": "x",
    "Categoria": "Fotovoltaico Industriale",
    "Power": 290.4,
    "Producibilit?": 970.3811,
    "Energia Prodotta": "282 MWh/anno",
    "Energia Prodotta 25": "7.045 MWh",
    "Alberi": "10.760 alberi",
    "CO2  risparmiato": "1.796 ton.",
    "Risparmio": "? 1.408.993",
    "TEP": "606 TEP",
    "latitude": "45.5039",
    "longitude": "9.0256"
  },
  {
    "CTR + Percorso cartella": "IMP24_004 - BENNET SPA Novi Ligure",
    "Nominativo": "Bennet SPA",
    "Coordinate X": "44.7625",
    "Coordinate Y": "8.7856",
    "Tipologia": "Novi Ligure, Alessandria",
    "Tipologia Description": "x",
    "Categoria": "Fotovoltaico Industriale",
    "Power": 437.8,
    "Producibilit?": 1177.6949,
    "Energia Prodotta": "516 MWh/anno",
    "Energia Prodotta 25": "12.890 MWh",
    "Alberi": "19.690 alberi",
    "CO2  risparmiato": "3.287 ton.",
    "Risparmio": "? 2.577.974",
    "TEP": "1.108 TEP",
    "latitude": "44.7625",
    "longitude": "8.7856"
  },
  {
    "CTR + Percorso cartella": "IMP24_007 - CANTINA VALTIDONE S.C.A.R.L",
    "Nominativo": "Cantina Valtidone S.C.A.R.L.",
    "Coordinate X": "45.0172",
    "Coordinate Y": "9.4447",
    "Tipologia": "Borgonovo Val Tidone, Piacenza",
    "Tipologia Description": "x",
    "Categoria": "Fotovoltaico Industriale",
    "Power": 398.01,
    "Producibilit?": 1030.4034,
    "Energia Prodotta": "410 MWh/anno",
    "Energia Prodotta 25": "10.253 MWh",
    "Alberi": "15.660 alberi",
    "CO2  risparmiato": "2.614 ton.",
    "Risparmio": "? 2.050.554",
    "TEP": "882 TEP",
    "latitude": "45.0172",
    "longitude": "9.4447"
  },
  {
    "CTR + Percorso cartella": "IMP24_008 - BOMOCAF S.R.L",
    "Nominativo": "Bomocaf S.R.L.",
    "Coordinate X": "45.3339",
    "Coordinate Y": "9.1028",
    "Tipologia": "Binasco, Milano",
    "Tipologia Description": "x",
    "Categoria": "Fotovoltaico Industriale",
    "Power": 119.52,
    "Producibilit?": 983.5763,
    "Energia Prodotta": "118 MWh/anno",
    "Energia Prodotta 25": "2.939 MWh",
    "Alberi": "4.490 alberi",
    "CO2  risparmiato": "749 ton.",
    "Risparmio": "? 587.785",
    "TEP": "253 TEP",
    "latitude": "45.3339",
    "longitude": "9.1028"
  },
  {
    "CTR + Percorso cartella": "IMP24_009 - ARIETE SRL",
    "Nominativo": "Ariete SRL",
    "Coordinate X": "44.194579080114266",
    "Coordinate Y": "8.126780975983715",
    "Tipologia": "Bardineto, Savona",
    "Tipologia Description": "x",
    "Categoria": "Fotovoltaico Industriale",
    "Power": 34.86,
    "Producibilit?": 1090.0746,
    "Energia Prodotta": "38.000 kWh/anno",
    "Energia Prodotta 25": "950.000 kWh",
    "Alberi": "1.460 alberi",
    "CO2  risparmiato": "242 ton.",
    "Risparmio": "? 190.000",
    "TEP": "82 TEP",
    "latitude": "44.194579080114266",
    "longitude": "8.126780975983715"
  },
  {
    "CTR + Percorso cartella": "IMP25_001 - EURORISTORAZIONE SRL",
    "Nominativo": "Euroristorazione SRL",
    "Coordinate X": "45.6608",
    "Coordinate Y": "8.7947",
    "Tipologia": "Gallarate, Varese",
    "Tipologia Description": "x",
    "Categoria": "Fotovoltaico Industriale",
    "Power": 25.5,
    "Producibilit?": 1180,
    "Energia Prodotta": "30.090 kWh/anno",
    "Energia Prodotta 25": "752.250 kWh",
    "Alberi": "1.150 alberi",
    "CO2  risparmiato": "192 ton.",
    "Risparmio": "? 150.450",
    "TEP": "65 TEP",
    "latitude": "45.6608",
    "longitude": "8.7947"
  },
  {
    "CTR + Percorso cartella": "Z:\\CLIENTI\\13 - ECOBONUS\\2021\\ECO21_061 - BRAGHERI ATTILIO\\Documentazione completa",
    "Nominativo": "Braghieri Attilio",
    "Coordinate X": "45.317187968885406",
    "Coordinate Y": "8.845153487707332",
    "Tipologia": "Vigevano, Pavia",
    "Tipologia Description": "x",
    "Categoria": "Superbonus",
    "Power": 9.02,
    "Producibilit?": 1086,
    "Energia Prodotta": "9.796 kWh/anno",
    "Energia Prodotta 25": "244.893 kWh",
    "Alberi": "380 alberi",
    "CO2  risparmiato": "62.448 kg",
    "Risparmio": "? 48.979",
    "TEP": "21 TEP",
    "latitude": "45.317187968885406",
    "longitude": "8.845153487707332"
  },
  {
    "CTR + Percorso cartella": "EST19_001 - MALTA INTERNATIONAL AIRPORT",
    "Nominativo": "Malta International Airport",
    "Coordinate X": "35.848124641908285",
    "Coordinate Y": "14.49843151104255",
    "Tipologia": "Luqa, Malta",
    "Tipologia Description": "x",
    "Categoria": "Fotovoltaico Estero",
    "Power": 780,
    "Producibilit?": 1579,
    "Energia Prodotta": "1.232 MWh/anno",
    "Energia Prodotta 25": "30.791 MWh",
    "Alberi": "47.020 alberi",
    "CO2  risparmiato": "7.852 ton.",
    "Risparmio": "? 6.158.100",
    "TEP": "2.648 TEP",
    "latitude": "35.848124641908285",
    "longitude": "14.49843151104255"
  },
  {
    "CTR + Percorso cartella": "EST21_001 - MYENERGY LIMITED-GOZO",
    "Nominativo": "Malta Limited",
    "Coordinate X": "36.02045105420066",
    "Coordinate Y": "14.249544265827925",
    "Tipologia": "Gozo, Malta",
    "Categoria": "Fotovoltaico Estero",
    "Power": 699.46,
    "Producibilit?": 1571.212077888657,
    "Energia Prodotta": "1.099.000 kWh/anno",
    "Energia Prodotta 25": "27.475 MWh",
    "Alberi": "41.960 alberi",
    "CO2  risparmiato": "7.006 ton.",
    "Risparmio": "? 5.495.000",
    "TEP": "2.362 TEP",
    "latitude": "36.02045105420066",
    "longitude": "14.249544265827925"
  }
]